broadlink/__init__.py
broadlink/alarm.py
broadlink/climate.py
broadlink/const.py
broadlink/cover.py
broadlink/device.py
broadlink/exceptions.py
broadlink/helpers.py
broadlink/hub.py
broadlink/light.py
broadlink/protocol.py
broadlink/remote.py
broadlink/sensor.py
broadlink/switch.py
broadlink-0.18.3.dist-info/LICENSE
broadlink-0.18.3.dist-info/METADATA
broadlink-0.18.3.dist-info/WHEEL
broadlink-0.18.3.dist-info/top_level.txt
broadlink-0.18.3.dist-info/RECORD
