Metadata-Version: 2.1
Name: broadlink
Version: 0.18.3
Summary: Python API for controlling Broadlink devices
Home-page: http://github.com/mjg59/python-broadlink
Author: Matthew Garrett
Author-email: mjg59@srcf.ucam.org
License: UNKNOWN
Platform: UNKNOWN
Classifier: Development Status :: 4 - Beta
Classifier: Intended Audience :: Developers
Classifier: License :: OSI Approved :: MIT License
Classifier: Operating System :: OS Independent
Classifier: Programming Language :: Python
License-File: LICENSE
Requires-Dist: cryptography (>=3.2)
